{
  "project_info": {
    "project_number": "911424750663",
    "project_id": "foodar-a85bf",
    "storage_bucket": "foodar-a85bf.firebasestorage.app"
  },
  "client": [
    {
      "client_info": {
        "mobilesdk_app_id": "1:911424750663:android:86468c702dd0970ef41d62",
        "android_client_info": {
          "package_name": "com.capstone.foodar"
        }
      },
      "oauth_client": [],
      "api_key": [
        {
          "current_key": "AIzaSyAf9A_3Go99mkDaHyxPxVgVxHRzdlcMJLM"
        }
      ],
      "services": {
        "appinvite_service": {
          "other_platform_oauth_client": []
        }
      }
    }
  ],
  "configuration_version": "1"
}